<?xml version="1.0" encoding="UTF-8"?>
<metadata xml:lang="zh"><Esri><CreaDate>20170120</CreaDate><CreaTime>18562900</CreaTime><SyncOnce>FALSE</SyncOnce><DataProperties><itemProps><itemLocation><linkage Sync="TRUE">file://\\LIUWEI-PC\C$\Users\Administrator\Documents\ArcGIS\Default.gdb</linkage><protocol Sync="TRUE">Local Area Network</protocol></itemLocation><itemName Sync="TRUE">县行政区_Dissolve</itemName><imsContentType Sync="TRUE">002</imsContentType></itemProps><copyHistory><copy source="F:\工作\ArcGIS相关\GISerClub\数据\基础地理数据\全国1比400万A\县级行政界线\BOUNT_poly" dest="\\EDISON-PC\F\工作\ArcGIS相关\GISerClub\数据\ex13-1\BOUNT_poly" date="20141013" time="16520400"></copy></copyHistory><lineage><Process ToolSource="C:\Program Files\ArcGIS\Desktop10.0\ArcToolbox\Toolboxes\Data Management Tools.tbx\CalculateField" Date="20141013" Time="165320">CalculateField 县行政区 NAME [NAME99] VB #</Process><Process ToolSource="C:\Program Files\ArcGIS\Desktop10.0\ArcToolbox\Toolboxes\Data Management Tools.tbx\CalculateField" Date="20141013" Time="165348">CalculateField 县行政区 ProvinceId [SH2] VB #</Process><Process ToolSource="G:\arcgis\Desktop10.0\ArcToolbox\Toolboxes\Data Management Tools.tbx\Dissolve" Date="20170120" Time="164145">Dissolve 县行政区 C:\Users\Administrator\Documents\ArcGIS\Default.gdb\县行政区_Dissolve ProvinceId # MULTI_PART DISSOLVE_LINES</Process></lineage></DataProperties><SyncDate>20170120</SyncDate><SyncTime>16413800</SyncTime><ModDate>20170120</ModDate><ModTime>16413800</ModTime><ArcGISFormat>1.0</ArcGISFormat></Esri><dataIdInfo><envirDesc Sync="TRUE">Microsoft Windows Server 2008 R2 Version 6.1 (Build 7601) Service Pack 1; ESRI ArcGIS 10.0.0.2414</envirDesc><dataLang><languageCode value="zho" country="CHN"></languageCode></dataLang><idCitation><resTitle Sync="TRUE">县行政区_Dissolve</resTitle><presForm><PresFormCd value="005"></PresFormCd></presForm></idCitation><descKeys><thesaName uuidref="723f6998-058e-11dc-8314-0800200c9a66"></thesaName><keyword Sync="TRUE">002</keyword></descKeys><spatRpType><SpatRepTypCd value="001"></SpatRepTypCd></spatRpType></dataIdInfo><mdLang><languageCode value="zho"></languageCode></mdLang><distInfo><distFormat><formatName Sync="TRUE">文件地理数据库要素类</formatName></distFormat></distInfo><mdHrLv><ScopeCd value="005"></ScopeCd></mdHrLv><mdHrLvName Sync="TRUE">dataset</mdHrLvName><spdoinfo><ptvctinf><esriterm Name="县行政区_Dissolve"><efeatyp Sync="TRUE">Simple</efeatyp><efeageom Sync="TRUE">4</efeageom><esritopo Sync="TRUE">FALSE</esritopo><efeacnt Sync="TRUE">0</efeacnt><spindex Sync="TRUE">TRUE</spindex><linrefer Sync="TRUE">FALSE</linrefer></esriterm></ptvctinf></spdoinfo><spatRepInfo><VectSpatRep><topLvl><TopoLevCd value="001"></TopoLevCd></topLvl><geometObjs><geoObjTyp><GeoObjTypCd value="002"></GeoObjTypCd><geoObjCnt Sync="TRUE">0</geoObjCnt></geoObjTyp></geometObjs></VectSpatRep></spatRepInfo><eainfo><detailed Name="县行政区_Dissolve"><enttyp><enttypl Sync="TRUE">县行政区_Dissolve</enttypl><enttypt Sync="TRUE">Feature Class</enttypt><enttypc Sync="TRUE">0</enttypc></enttyp><attr><attrlabl Sync="TRUE">OBJECTID</attrlabl><attalias Sync="TRUE">OBJECTID</attalias><attrtype Sync="TRUE">OID</attrtype><attwidth Sync="TRUE">4</attwidth><atprecis Sync="TRUE">0</atprecis><attscale Sync="TRUE">0</attscale><attrdef Sync="TRUE">Internal feature number.</attrdef><attrdefs Sync="TRUE">ESRI</attrdefs><attrdomv><udom Sync="TRUE">Sequential unique whole numbers that are automatically generated.</udom></attrdomv></attr><attr><attrlabl Sync="TRUE">Shape</attrlabl><attalias Sync="TRUE">Shape</attalias><attrtype Sync="TRUE">Geometry</attrtype><attwidth Sync="TRUE">0</attwidth><atprecis Sync="TRUE">0</atprecis><attscale Sync="TRUE">0</attscale><attrdef Sync="TRUE">Feature geometry.</attrdef><attrdefs Sync="TRUE">ESRI</attrdefs><attrdomv><udom Sync="TRUE">Coordinates defining the features.</udom></attrdomv></attr><attr><attrlabl Sync="TRUE">ProvinceId</attrlabl><attalias Sync="TRUE">ProvinceId</attalias><attrtype Sync="TRUE">SmallInteger</attrtype><attwidth Sync="TRUE">2</attwidth><atprecis Sync="TRUE">0</atprecis><attscale Sync="TRUE">0</attscale></attr><attr><attrlabl Sync="TRUE">Shape_Length</attrlabl><attalias Sync="TRUE">Shape_Length</attalias><attrtype Sync="TRUE">Double</attrtype><attwidth Sync="TRUE">8</attwidth><atprecis Sync="TRUE">0</atprecis><attscale Sync="TRUE">0</attscale><attrdef Sync="TRUE">Length of feature in internal units.</attrdef><attrdefs Sync="TRUE">ESRI</attrdefs><attrdomv><udom Sync="TRUE">Positive real numbers that are automatically generated.</udom></attrdomv></attr><attr><attrlabl Sync="TRUE">Shape_Area</attrlabl><attalias Sync="TRUE">Shape_Area</attalias><attrtype Sync="TRUE">Double</attrtype><attwidth Sync="TRUE">8</attwidth><atprecis Sync="TRUE">0</atprecis><attscale Sync="TRUE">0</attscale><attrdef Sync="TRUE">Area of feature in internal units squared.</attrdef><attrdefs Sync="TRUE">ESRI</attrdefs><attrdomv><udom Sync="TRUE">Positive real numbers that are automatically generated.</udom></attrdomv></attr></detailed></eainfo><mdDateSt Sync="TRUE">20170120</mdDateSt></metadata>
